frontmatter_mcp/__init__.py
frontmatter_mcp/dependencies.py
frontmatter_mcp/files.py
frontmatter_mcp/query.py
frontmatter_mcp/query_schema.py
frontmatter_mcp/server.py
frontmatter_mcp/settings.py
frontmatter_mcp/semantic/__init__.py
frontmatter_mcp/semantic/cache.py
frontmatter_mcp/semantic/context.py
frontmatter_mcp/semantic/indexer.py
frontmatter_mcp/semantic/model.py
frontmatter_mcp/semantic/query.py
frontmatter_mcp/semantic/query_schema.py
frontmatter_mcp-0.5.3.dist-info/METADATA
frontmatter_mcp-0.5.3.dist-info/WHEEL
frontmatter_mcp-0.5.3.dist-info/entry_points.txt
frontmatter_mcp-0.5.3.dist-info/licenses/LICENSE
frontmatter_mcp-0.5.3.dist-info/RECORD
