Metadata-Version: 2.4
Name: frontmatter-mcp
Version: 0.5.3
Summary: MCP server for querying Markdown frontmatter with DuckDB SQL
Project-URL: Homepage, https://github.com/kzmshx/frontmatter-mcp
Project-URL: Repository, https://github.com/kzmshx/frontmatter-mcp
Author: kzmshx
License: MIT License
License-File: LICENSE
Requires-Python: >=3.11
Requires-Dist: duckdb<2.0.0,>=1.0.0
Requires-Dist: fastmcp<3.0.0,>=2.14.0
Requires-Dist: pyarrow<26.0.0,>=22.0.0
Requires-Dist: pydantic-settings<3.0.0,>=2.0.0
Requires-Dist: python-frontmatter<2.0.0,>=1.0.0
Provides-Extra: semantic
Requires-Dist: protobuf<6.0.0,>=3.0.0; extra == 'semantic'
Requires-Dist: sentence-transformers<6.0.0,>=2.0.0; extra == 'semantic'
Requires-Dist: sentencepiece<1.0.0,>=0.1.0; extra == 'semantic'
